exp_manager/__init__.py
exp_manager/__main__.py
exp_manager/empty_run_info.yaml
exp_manager/exp_manager.py
exp_manager/parser.py
exp_manager/run.py
exp_manager/utils.py
exp_manager-0.1.7.dist-info/entry_points.txt
exp_manager-0.1.7.dist-info/WHEEL
exp_manager-0.1.7.dist-info/METADATA
exp_manager-0.1.7.dist-info/RECORD
